setup.py
pypjval.egg-info/PKG-INFO
pypjval.egg-info/SOURCES.txt
pypjval.egg-info/dependency_links.txt
pypjval.egg-info/requires.txt
pypjval.egg-info/top_level.txt
pyprjval/__init__.py
pyprjval/_val.py