Metadata-Version: 2.1
Name: pypjval
Version: 1.0.0
Summary: py project validator
Home-page: https://github.com/yaty30/pyprjval
Author: James Yip
Author-email: contact@thejamesyip.com
License: BSD 2-clause
Classifier: Development Status :: 1 - Planning
Classifier: Intended Audience :: Science/Research
Classifier: License :: OSI Approved :: BSD License
Classifier: Operating System :: POSIX :: Linux
Classifier: Programming Language :: Python :: 2
Classifier: Programming Language :: Python :: 2.7
Classifier: Programming Language :: Python :: 3
Classifier: Programming Language :: Python :: 3.4
Classifier: Programming Language :: Python :: 3.5
